borgstats/_version.py
borgstats/borgstats.py
borgstats-1.0.1.dist-info/METADATA
borgstats-1.0.1.dist-info/WHEEL
borgstats-1.0.1.dist-info/entry_points.txt
borgstats-1.0.1.dist-info/top_level.txt
borgstats-1.0.1.dist-info/RECORD
