Metadata-Version: 2.4
Name: borgstats
Version: 1.0.1
Summary: Get various statistics from borg or borgmagic.
Author-email: Jason Lingohr <jason@lucid.net.au>
Project-URL: Homepage, https://gitlab.lucid.net.au/lucid/borgstats
Project-URL: Issues, https://gitlab.lucid.net.au/lucid/borgstats/-/issues
Classifier: Programming Language :: Python :: 3
Classifier: License :: OSI Approved :: GNU General Public License v3 or later (GPLv3+)
Classifier: Operating System :: OS Independent
Requires-Python: >=3.9
Requires-Dist: click
Requires-Dist: humanize
Requires-Dist: rich
